LICENSE
MANIFEST.in
README.rst
requirements.txt
setup.py
sequanix/__init__.py
sequanix/sequanix.py
sequanix/utils.py
sequanix.egg-info/PKG-INFO
sequanix.egg-info/SOURCES.txt
sequanix.egg-info/dependency_links.txt
sequanix.egg-info/entry_points.txt
sequanix.egg-info/requires.txt
sequanix.egg-info/top_level.txt
sequanix/media/__init__.py
sequanix/ui/__init__.py
sequanix/ui/ui_help.py
sequanix/ui/ui_mainwindow.py
sequanix/ui/ui_preferences.py
sequanix/ui/ui_snakemake.py
sequanix/widgets/__init__.py
sequanix/widgets/about.py
sequanix/widgets/browser.py
sequanix/widgets/file_browser.py
sequanix/widgets/help.py
sequanix/widgets/ipython.py
sequanix/widgets/messages.py
sequanix/widgets/preferences.py
sequanix/widgets/snakemake.py
sequanix/widgets/tools.py
sequanix/widgets/widgets.py