Metadata-Version: 2.1
Name: sequanix
Version: 0.2.0
Summary: Sequanix is a graphical user interface (GUI) that can be used to run Snakemake workflows
Home-page: https://github.com/sequana/sequanix
Author: Sequana Team
Project-URL: Bug Tracker, https://github.com/sequana/sequanix/issues
Classifier: Programming Language :: Python :: 3
Classifier: License :: OSI Approved :: BSD License
Classifier: Operating System :: Unix
Provides-Extra: testing
Provides-Extra: pipelines
Provides-Extra: doc
License-File: LICENSE
